lwe2d/engine/__init__.py
lwe2d/engine/core.py
lwe2d/engine/entity.py
lwe2d/engine/renderer.py
lwe2d/examples/__init__.py
lwe2d/examples/player.py
lwe2d/examples/shapes.py
lwe2d/examples/engine/__init__.py
lwe2d/examples/engine/core.py
lwe2d/examples/engine/entity.py
lwe2d/examples/engine/renderer.py
lwe2d-0.0.2.dist-info/licenses/LICENSE
lwe2d-0.0.2.dist-info/METADATA
lwe2d-0.0.2.dist-info/WHEEL
lwe2d-0.0.2.dist-info/top_level.txt
lwe2d-0.0.2.dist-info/RECORD
