Metadata-Version: 2.4
Name: lwe2d
Version: 0.0.2
Summary: LWE2D is a lightweight 2D game engine built using Pygame.
Requires-Python: >=3.13
License-File: LICENSE
Dynamic: license-file
